claude_post_mcp_server-0.1.9.dist-info/licenses/LICENSE
email_client/__init__.py
email_client/main.py
email_client/server.py
claude_post_mcp_server-0.1.9.dist-info/METADATA
claude_post_mcp_server-0.1.9.dist-info/WHEEL
claude_post_mcp_server-0.1.9.dist-info/entry_points.txt
claude_post_mcp_server-0.1.9.dist-info/top_level.txt
claude_post_mcp_server-0.1.9.dist-info/RECORD
